{"cameraMode":{"drawMode":0,"name":"Shaded","section":"Shading Mode"},"sceneLighting":true,"audioPlay":false,"sceneViewState":{"showFog":true,"showMaterialUpdate":false,"showSkybox":true,"showFlares":true,"showImageEffects":true,"showParticleSystems":true,"showVisualEffectGraphs":true,"m_FxEnabled":true},"in2DMode":false,"pivot":{"x":26.02764892578125,"y":4.301441192626953,"z":-8.75599479675293},"rotation":{"x":0.11960271000862122,"y":0.849310576915741,"z":-0.21812908351421357,"w":0.465670645236969},"size":27.23550033569336,"orthographic":false}